check_self_class_call_of_meta_package/__init__.py
check_self_class_call_of_meta_package/check_self_class_call_of_meta_module.py
multivalued_dict_package/__init__.py
multivalued_dict_package/doctestmod_module.py
multivalued_dict_package/multivalued_dict_module.py
multivalued_dict-2.0.1.dist-info/LICENSE
multivalued_dict-2.0.1.dist-info/METADATA
multivalued_dict-2.0.1.dist-info/WHEEL
multivalued_dict-2.0.1.dist-info/top_level.txt
multivalued_dict-2.0.1.dist-info/RECORD
