Metadata-Version: 2.1
Name: multivalued-dict
Version: 2.0.1
Summary: Multivalued dictionary package in python.
Home-page: https://github.com/fsssosei/MultivaluedDict
Author: sosei
Author-email: fss.sosei@gmail.com
License: GNU Affero General Public License v3
Keywords: multivalued,dictionary
Platform: UNKNOWN
Classifier: Development Status :: 5 - Production/Stable
Classifier: License :: OSI Approved :: GNU Affero General Public License v3
Classifier: Programming Language :: Python :: 3.7
Requires-Python: >=3.7
